README.rst
setup.py
bynamodb/__init__.py
bynamodb/attributes.py
bynamodb/conditions.py
bynamodb/exceptions.py
bynamodb/filterexps.py
bynamodb/indexes.py
bynamodb/model.py
bynamodb/patcher.py
bynamodb/results.py
bynamodb/version.py
bynamodb.egg-info/PKG-INFO
bynamodb.egg-info/SOURCES.txt
bynamodb.egg-info/dependency_links.txt
bynamodb.egg-info/requires.txt
bynamodb.egg-info/top_level.txt