Metadata-Version: 1.0
Name: bynamodb
Version: 0.1.1
Summary: High-Level DynamoDB Interface for Pythonwrapping Low-Level Interface of boto
Home-page: https://github.com/teddychoi/BynamoDB
Author: Bochul Choi
Author-email: vio.bo94@gmail.com
License: MIT
Platform: UNKNOWN
